{
  "publicPath": "",
  "all": [
    "client.bundle.js"
  ],
  "initial": [
    "client.bundle.js"
  ],
  "async": [],
  "modules": {
    "b6b79ef0": [
      0
    ],
    "3c8f2013": [
      0
    ],
    "2cbbdc3d": [
      0
    ],
    "b107bae0": [
      0
    ],
    "559fdae6": [
      0
    ],
    "7a417ce8": [
      0
    ],
    "13c198ed": [
      0
    ],
    "d6f6ee58": [
      0
    ],
    "68cd6898": [
      0
    ],
    "5983dcbe": [
      0
    ],
    "4d90be8a": [
      0
    ],
    "dc52d71e": [
      0
    ],
    "b9c58cfc": [
      0
    ],
    "0e8cfaf6": [
      0
    ],
    "3ce90463": [
      0
    ],
    "90c3b668": [
      0
    ],
    "a3182082": [
      0
    ],
    "fc0c24ee": [
      0
    ],
    "2a80601e": [
      0
    ]
  }
}